hsi2rgb_gui/hsi4viz.py
hsi2rgb_gui/web.py
hsi2rgb_gui-1.2.2.dist-info/METADATA
hsi2rgb_gui-1.2.2.dist-info/WHEEL
hsi2rgb_gui-1.2.2.dist-info/entry_points.txt
hsi2rgb_gui-1.2.2.dist-info/licenses/LICENSE
hsi2rgb_gui-1.2.2.dist-info/RECORD
