Metadata-Version: 2.4
Name: hsi2rgb-gui
Version: 1.2.2
Summary: Easily convert a hyperspectral image to an RGB image.
License:                     GNU AFFERO GENERAL PUBLIC LICENSE
License-File: LICENSE
Classifier: Programming Language :: Python
Classifier: Programming Language :: Python :: 3.10
Classifier: Programming Language :: Python :: 3.11
Classifier: Programming Language :: Python :: 3.12
Classifier: Programming Language :: Python :: 3.13
Classifier: Programming Language :: Python :: Implementation :: CPython
Requires-Python: >=3.13
Requires-Dist: einops>=0.8.0
Requires-Dist: gradio>=5.9.1
Requires-Dist: hsi2rgb>=0.1.0
Requires-Dist: matplotlib>=3.10.0
Requires-Dist: numpy>=2.2.1
Requires-Dist: scikit-image>=0.25.0
Requires-Dist: scipy>=1.14.1
